{
  "PortableSize": 39526741,
  "PortableHash": "8F070DEF9240A17993A1CA6A50B49C359BA8D8CFDA2D9267946E68F4BA9AA5C4",
  "Version": "0.8.3-preview.1",
  "Architecture": "arm64",
  "InstallSize": 0,
  "BuildTime": "2023-07-12T09:53:36.8337079+00:00",
  "Portable": "https://starward.scighost.com/release/package/Starward_Portable_0.8.3-preview.1_arm64.7z",
  "Install": null,
  "SeparatePrefix": "https://starward.scighost.com/release/separate_files/",
  "DisableAutoUpdate": false,
  "InstallHash": null
}
