{
  "retcode": 0,
  "message": "",
  "data": {
    "game": "nap",
    "lang": "vi-vn",
    "list": [
      {
        "id": 1011,
        "name": "Anby",
        "icon": "https://act-webstatic.hoyoverse.com/game_record/zzzv2/role_square_avatar/role_square_avatar_1011.png",
        "rarity": 3,
        "element_type": 203,
        "profession": 2
      },
      {
        "id": 1021,
        "name": "Nekomata",
        "icon": "https://act-webstatic.hoyoverse.com/game_record/zzzv2/role_square_avatar/role_square_avatar_1021.png",
        "rarity": 4,
        "element_type": 200,
        "profession": 1
      },
      {
        "id": 1031,
        "name": "Nicole",
        "icon": "https://act-webstatic.hoyoverse.com/game_record/zzzv2/role_square_avatar/role_square_avatar_1031.png",
        "rarity": 3,
        "element_type": 205,
        "profession": 4
      },
      {
        "id": 1041,
        "name": "Chiến Binh 11",
        "icon": "https://act-webstatic.hoyoverse.com/game_record/zzzv2/role_square_avatar/role_square_avatar_1041.png",
        "rarity": 4,
        "element_type": 201,
        "profession": 1
      },
      {
        "id": 1061,
        "name": "Corin",
        "icon": "https://act-webstatic.hoyoverse.com/game_record/zzzv2/role_square_avatar/role_square_avatar_1061.png",
        "rarity": 3,
        "element_type": 200,
        "profession": 1
      },
      {
        "id": 1071,
        "name": "Caesar",
        "icon": "https://act-webstatic.hoyoverse.com/game_record/zzzv2/role_square_avatar/role_square_avatar_1071.png",
        "rarity": 4,
        "element_type": 200,
        "profession": 5
      },
      {
        "id": 1081,
        "name": "Billy",
        "icon": "https://act-webstatic.hoyoverse.com/game_record/zzzv2/role_square_avatar/role_square_avatar_1081.png",
        "rarity": 3,
        "element_type": 200,
        "profession": 1
      },
      {
        "id": 1091,
        "name": "Miyabi",
        "icon": "https://act-webstatic.hoyoverse.com/game_record/zzzv2/role_square_avatar/role_square_avatar_1091.png",
        "rarity": 4,
        "element_type": 202,
        "profession": 3
      },
      {
        "id": 1101,
        "name": "Koleda",
        "icon": "https://act-webstatic.hoyoverse.com/game_record/zzzv2/role_square_avatar/role_square_avatar_1101.png",
        "rarity": 4,
        "element_type": 201,
        "profession": 2
      },
      {
        "id": 1111,
        "name": "Anton",
        "icon": "https://act-webstatic.hoyoverse.com/game_record/zzzv2/role_square_avatar/role_square_avatar_1111.png",
        "rarity": 3,
        "element_type": 203,
        "profession": 1
      },
      {
        "id": 1121,
        "name": "Ben",
        "icon": "https://act-webstatic.hoyoverse.com/game_record/zzzv2/role_square_avatar/role_square_avatar_1121.png",
        "rarity": 3,
        "element_type": 201,
        "profession": 5
      },
      {
        "id": 1131,
        "name": "Soukaku",
        "icon": "https://act-webstatic.hoyoverse.com/game_record/zzzv2/role_square_avatar/role_square_avatar_1131.png",
        "rarity": 3,
        "element_type": 202,
        "profession": 4
      },
      {
        "id": 1141,
        "name": "Lycaon",
        "icon": "https://act-webstatic.hoyoverse.com/game_record/zzzv2/role_square_avatar/role_square_avatar_1141.png",
        "rarity": 4,
        "element_type": 202,
        "profession": 2
      },
      {
        "id": 1151,
        "name": "Lucy",
        "icon": "https://act-webstatic.hoyoverse.com/game_record/zzzv2/role_square_avatar/role_square_avatar_1151.png",
        "rarity": 3,
        "element_type": 201,
        "profession": 4
      },
      {
        "id": 1161,
        "name": "Lighter",
        "icon": "https://act-webstatic.hoyoverse.com/game_record/zzzv2/role_square_avatar/role_square_avatar_1161.png",
        "rarity": 4,
        "element_type": 201,
        "profession": 2
      },
      {
        "id": 1171,
        "name": "Burnice",
        "icon": "https://act-webstatic.hoyoverse.com/game_record/zzzv2/role_square_avatar/role_square_avatar_1171.png",
        "rarity": 4,
        "element_type": 201,
        "profession": 3
      },
      {
        "id": 1181,
        "name": "Grace",
        "icon": "https://act-webstatic.hoyoverse.com/game_record/zzzv2/role_square_avatar/role_square_avatar_1181.png",
        "rarity": 4,
        "element_type": 203,
        "profession": 3
      },
      {
        "id": 1191,
        "name": "Ellen",
        "icon": "https://act-webstatic.hoyoverse.com/game_record/zzzv2/role_square_avatar/role_square_avatar_1191.png",
        "rarity": 4,
        "element_type": 202,
        "profession": 1
      },
      {
        "id": 1201,
        "name": "Harumasa",
        "icon": "https://act-webstatic.hoyoverse.com/game_record/zzzv2/role_square_avatar/role_square_avatar_1201.png",
        "rarity": 4,
        "element_type": 203,
        "profession": 1
      },
      {
        "id": 1211,
        "name": "Rina",
        "icon": "https://act-webstatic.hoyoverse.com/game_record/zzzv2/role_square_avatar/role_square_avatar_1211.png",
        "rarity": 4,
        "element_type": 203,
        "profession": 4
      },
      {
        "id": 1221,
        "name": "Yanagi",
        "icon": "https://act-webstatic.hoyoverse.com/game_record/zzzv2/role_square_avatar/role_square_avatar_1221.png",
        "rarity": 4,
        "element_type": 203,
        "profession": 3
      },
      {
        "id": 1241,
        "name": "Zhu Yuan",
        "icon": "https://act-webstatic.hoyoverse.com/game_record/zzzv2/role_square_avatar/role_square_avatar_1241.png",
        "rarity": 4,
        "element_type": 205,
        "profession": 1
      },
      {
        "id": 1251,
        "name": "Qingyi",
        "icon": "https://act-webstatic.hoyoverse.com/game_record/zzzv2/role_square_avatar/role_square_avatar_1251.png",
        "rarity": 4,
        "element_type": 203,
        "profession": 2
      },
      {
        "id": 1261,
        "name": "Jane",
        "icon": "https://act-webstatic.hoyoverse.com/game_record/zzzv2/role_square_avatar/role_square_avatar_1261.png",
        "rarity": 4,
        "element_type": 200,
        "profession": 3
      },
      {
        "id": 1271,
        "name": "Seth",
        "icon": "https://act-webstatic.hoyoverse.com/game_record/zzzv2/role_square_avatar/role_square_avatar_1271.png",
        "rarity": 3,
        "element_type": 203,
        "profession": 5
      },
      {
        "id": 1281,
        "name": "Piper",
        "icon": "https://act-webstatic.hoyoverse.com/game_record/zzzv2/role_square_avatar/role_square_avatar_1281.png",
        "rarity": 3,
        "element_type": 200,
        "profession": 3
      },
      {
        "id": 1311,
        "name": "Astra Yao",
        "icon": "https://act-webstatic.hoyoverse.com/game_record/zzzv2/role_square_avatar/role_square_avatar_1311.png",
        "rarity": 4,
        "element_type": 205,
        "profession": 4
      },
      {
        "id": 1321,
        "name": "Evelyn",
        "icon": "https://act-webstatic.hoyoverse.com/game_record/zzzv2/role_square_avatar/role_square_avatar_1321.png",
        "rarity": 4,
        "element_type": 201,
        "profession": 1
      },
      {
        "id": 1351,
        "name": "Pulchra",
        "icon": "https://act-webstatic.hoyoverse.com/game_record/zzzv2/role_square_avatar/role_square_avatar_1351.png",
        "rarity": 3,
        "element_type": 200,
        "profession": 2
      },
      {
        "id": 1361,
        "name": "Trigger",
        "icon": "https://act-webstatic.hoyoverse.com/game_record/zzzv2/role_square_avatar/role_square_avatar_1361.png",
        "rarity": 4,
        "element_type": 203,
        "profession": 2
      },
      {
        "id": 1381,
        "name": "Chiến Binh 0 - Anby",
        "icon": "https://act-webstatic.hoyoverse.com/game_record/zzzv2/role_square_avatar/role_square_avatar_1381.png",
        "rarity": 4,
        "element_type": 203,
        "profession": 1
      },
      {
        "id": 12001,
        "name": "[Pha Mặt Trăng] Pleniluna",
        "icon": "https://act-webstatic.hoyoverse.com/darkmatter/nap/prod_gf_cn/item_icon_u44f0b/a159652d74949dba16dd59b5c8ed9b18.png",
        "rarity": 2,
        "element_type": 0,
        "profession": 1
      },
      {
        "id": 12002,
        "name": "[Pha Mặt Trăng] Decrescent",
        "icon": "https://act-webstatic.hoyoverse.com/darkmatter/nap/prod_gf_cn/item_icon_u44f0b/f51128f1abf10ab8c817aae5784dd6ed.png",
        "rarity": 2,
        "element_type": 0,
        "profession": 1
      },
      {
        "id": 12003,
        "name": "[Pha Mặt Trăng] Noviluna",
        "icon": "https://act-webstatic.hoyoverse.com/darkmatter/nap/prod_gf_cn/item_icon_u44f0b/61d3cf060e87fadd5f7007322470b9cd.png",
        "rarity": 2,
        "element_type": 0,
        "profession": 1
      },
      {
        "id": 12004,
        "name": "[Âm Vang] Loại I",
        "icon": "https://act-webstatic.hoyoverse.com/darkmatter/nap/prod_gf_cn/item_icon_u44f0b/8b920140da2473716692767de8e184e6.png",
        "rarity": 2,
        "element_type": 0,
        "profession": 4
      },
      {
        "id": 12005,
        "name": "[Âm Vang] Loại II",
        "icon": "https://act-webstatic.hoyoverse.com/darkmatter/nap/prod_gf_cn/item_icon_u44f0b/45af41aedd82672c0d3817db6bc927ed.png",
        "rarity": 2,
        "element_type": 0,
        "profession": 4
      },
      {
        "id": 12006,
        "name": "[Âm Vang] Loại III",
        "icon": "https://act-webstatic.hoyoverse.com/darkmatter/nap/prod_gf_cn/item_icon_u44f0b/41016e585322e8af5a6e159e79874609.png",
        "rarity": 2,
        "element_type": 0,
        "profession": 4
      },
      {
        "id": 12007,
        "name": "[Nước Xiết] Dạng Súng",
        "icon": "https://act-webstatic.hoyoverse.com/darkmatter/nap/prod_gf_cn/item_icon_u44f0b/9dc4900867fc2ea68d55bfa9899af70b.png",
        "rarity": 2,
        "element_type": 0,
        "profession": 2
      },
      {
        "id": 12008,
        "name": "[Nước Xiết] Dạng Tiễn",
        "icon": "https://act-webstatic.hoyoverse.com/darkmatter/nap/prod_gf_cn/item_icon_u44f0b/e7081c9cd425afb604728428e58f73bd.png",
        "rarity": 2,
        "element_type": 0,
        "profession": 2
      },
      {
        "id": 12009,
        "name": "[Nước Xiết] Dạng Rìu",
        "icon": "https://act-webstatic.hoyoverse.com/darkmatter/nap/prod_gf_cn/item_icon_u44f0b/ffe051723294305b2810b79bfb7bd6a8.png",
        "rarity": 2,
        "element_type": 0,
        "profession": 2
      },
      {
        "id": 12010,
        "name": "[Bão Từ] Alpha",
        "icon": "https://act-webstatic.hoyoverse.com/darkmatter/nap/prod_gf_cn/item_icon_u44f0b/de449e1abf2abcd8870f3508a2493a69.png",
        "rarity": 2,
        "element_type": 0,
        "profession": 3
      },
      {
        "id": 12011,
        "name": "[Bão Từ] Bravo",
        "icon": "https://act-webstatic.hoyoverse.com/darkmatter/nap/prod_gf_cn/item_icon_u44f0b/840069d44220c323cfed57bc965ee522.png",
        "rarity": 2,
        "element_type": 0,
        "profession": 3
      },
      {
        "id": 12012,
        "name": "[Bão Từ] Charlie",
        "icon": "https://act-webstatic.hoyoverse.com/darkmatter/nap/prod_gf_cn/item_icon_u44f0b/60aba9202f2cdcd9a361799a516a5744.png",
        "rarity": 2,
        "element_type": 0,
        "profession": 3
      },
      {
        "id": 12013,
        "name": "[Hằng Đẳng Thức] Cơ Bản",
        "icon": "https://act-webstatic.hoyoverse.com/darkmatter/nap/prod_gf_cn/item_icon_u44f0b/e35d4e6996ab425cc53249a5f2e11c99.png",
        "rarity": 2,
        "element_type": 0,
        "profession": 5
      },
      {
        "id": 12014,
        "name": "[Hằng Đẳng Thức] Biến Cách",
        "icon": "https://act-webstatic.hoyoverse.com/darkmatter/nap/prod_gf_cn/item_icon_u44f0b/5bc577f2e468001fdfe13cf0ead7b1f2.png",
        "rarity": 2,
        "element_type": 0,
        "profession": 5
      },
      {
        "id": 13001,
        "name": "Siêu Sao Đường Phố",
        "icon": "https://act-webstatic.hoyoverse.com/darkmatter/nap/prod_gf_cn/item_icon_u44f0b/0e96a04fdb77c907bb61756f39cf0c2d.png",
        "rarity": 3,
        "element_type": 0,
        "profession": 1
      },
      {
        "id": 13002,
        "name": "Mảnh Ghép Thời Gian",
        "icon": "https://act-webstatic.hoyoverse.com/darkmatter/nap/prod_gf_cn/item_icon_u44f0b/53fd9cfa72dfce2f3aa3acfdcd1063d9.png",
        "rarity": 3,
        "element_type": 0,
        "profession": 4
      },
      {
        "id": 13003,
        "name": "Khách Tham Ăn Rừng Mưa",
        "icon": "https://act-webstatic.hoyoverse.com/darkmatter/nap/prod_gf_cn/item_icon_u44f0b/58d8898287786709dc5a09e1efae0906.png",
        "rarity": 3,
        "element_type": 0,
        "profession": 3
      },
      {
        "id": 13004,
        "name": "Engine Ánh Sao",
        "icon": "https://act-webstatic.hoyoverse.com/darkmatter/nap/prod_gf_cn/item_icon_u44f0b/9f50fb8ab0a636f01cba4197bba8e32e.png",
        "rarity": 3,
        "element_type": 0,
        "profession": 1
      },
      {
        "id": 13005,
        "name": "Cá Nằm Trên Thớt",
        "icon": "https://act-webstatic.hoyoverse.com/darkmatter/nap/prod_gf_cn/item_icon_u44f0b/222c4532b6dd882df90ce4d4bde934bf.png",
        "rarity": 3,
        "element_type": 0,
        "profession": 2
      },
      {
        "id": 13006,
        "name": "Lõi Hóa Thạch Quý",
        "icon": "https://act-webstatic.hoyoverse.com/darkmatter/nap/prod_gf_cn/item_icon_u44f0b/29409972779c9eb509fb95cba8027d89.png",
        "rarity": 3,
        "element_type": 0,
        "profession": 2
      },
      {
        "id": 13007,
        "name": "Máy Biến Hình Chính Hãng",
        "icon": "https://act-webstatic.hoyoverse.com/darkmatter/nap/prod_gf_cn/item_icon_u44f0b/82b7781a07b288ee10d5bf35aa6c9d1d.png",
        "rarity": 3,
        "element_type": 0,
        "profession": 5
      },
      {
        "id": 13008,
        "name": "Song Tinh Rơi Lệ",
        "icon": "https://act-webstatic.hoyoverse.com/darkmatter/nap/prod_gf_cn/item_icon_u44f0b/cf9b85341e205e97c839f7ecc9a74e82.png",
        "rarity": 3,
        "element_type": 0,
        "profession": 3
      },
      {
        "id": 13009,
        "name": "Son Môi Nhiễm Điện",
        "icon": "https://act-webstatic.hoyoverse.com/darkmatter/nap/prod_gf_cn/item_icon_u44f0b/7ecc9b7a790224a76c91cc7a0e4d695a.png",
        "rarity": 3,
        "element_type": 0,
        "profession": 3
      },
      {
        "id": 13010,
        "name": "Vòng Năng Lượng Thỏ",
        "icon": "https://act-webstatic.hoyoverse.com/darkmatter/nap/prod_gf_cn/item_icon_u44f0b/f9b2320addb755b2e4aeacd2964dddac.png",
        "rarity": 3,
        "element_type": 0,
        "profession": 5
      },
      {
        "id": 13011,
        "name": "Ngày Xuân Ấm Áp",
        "icon": "https://act-webstatic.hoyoverse.com/darkmatter/nap/prod_gf_cn/item_icon_u44f0b/1786785beaf6a3005ab8240492f15b6d.png",
        "rarity": 3,
        "element_type": 0,
        "profession": 5
      },
      {
        "id": 13013,
        "name": "Mùa Hoa Vàng Rực",
        "icon": "https://act-webstatic.hoyoverse.com/darkmatter/nap/prod_gf_cn/item_icon_u44f0b/e147a1dd7816a631e736b2576b6ab6ce.png",
        "rarity": 3,
        "element_type": 0,
        "profession": 1
      },
      {
        "id": 13015,
        "name": "Khát Vọng Cường Âm",
        "icon": "https://act-webstatic.hoyoverse.com/darkmatter/nap/prod_gf_cn/item_icon_u44f0b/c2705a3824b1dda60c864dc5f398bed6.png",
        "rarity": 3,
        "element_type": 0,
        "profession": 1
      },
      {
        "id": 13101,
        "name": "Pin Demara Loại II",
        "icon": "https://act-webstatic.hoyoverse.com/darkmatter/nap/prod_gf_cn/item_icon_u44f0b/0c28d69ca32f699f123302846e60679c.png",
        "rarity": 3,
        "element_type": 0,
        "profession": 2
      },
      {
        "id": 13103,
        "name": "Rương Kho Báu",
        "icon": "https://act-webstatic.hoyoverse.com/darkmatter/nap/prod_gf_cn/item_icon_u44f0b/0dfc1e26e042101cad0867fe58d9e628.png",
        "rarity": 3,
        "element_type": 0,
        "profession": 4
      },
      {
        "id": 13106,
        "name": "Nhân Viên Nội Trợ",
        "icon": "https://act-webstatic.hoyoverse.com/darkmatter/nap/prod_gf_cn/item_icon_u44f0b/38694701e391e007474220c4b1be0b12.png",
        "rarity": 3,
        "element_type": 0,
        "profession": 1
      },
      {
        "id": 13108,
        "name": "Engine Ánh Sao Mô Phỏng",
        "icon": "https://act-webstatic.hoyoverse.com/darkmatter/nap/prod_gf_cn/item_icon_u44f0b/8c9a8aa76066ee0af8fd0081aeb7e3f7.png",
        "rarity": 3,
        "element_type": 0,
        "profession": 1
      },
      {
        "id": 13111,
        "name": "Máy Khoan-Trục Đỏ",
        "icon": "https://act-webstatic.hoyoverse.com/darkmatter/nap/prod_gf_cn/item_icon_u44f0b/5046d8c1d9942485f034454b3bf748a0.png",
        "rarity": 3,
        "element_type": 0,
        "profession": 1
      },
      {
        "id": 13112,
        "name": "Xi Lanh Lớn",
        "icon": "https://act-webstatic.hoyoverse.com/darkmatter/nap/prod_gf_cn/item_icon_u44f0b/f7945564d2b3e439cccb2c7bdc204327.png",
        "rarity": 3,
        "element_type": 0,
        "profession": 5
      },
      {
        "id": 13113,
        "name": "Ác Diện Thẹn Thùng",
        "icon": "https://act-webstatic.hoyoverse.com/darkmatter/nap/prod_gf_cn/item_icon_u44f0b/03d6691857fb38464b4cdb679c3fb5b5.png",
        "rarity": 3,
        "element_type": 0,
        "profession": 4
      },
      {
        "id": 13115,
        "name": "Kaboom Hiếu Chiến",
        "icon": "https://act-webstatic.hoyoverse.com/darkmatter/nap/prod_gf_cn/item_icon_u44f0b/33dd18b562403f5a60d023de0467e048.png",
        "rarity": 3,
        "element_type": 0,
        "profession": 4
      },
      {
        "id": 13127,
        "name": "Duy Trì Trật Tự - Đặc Biệt",
        "icon": "https://act-webstatic.hoyoverse.com/darkmatter/nap/prod_gf_cn/item_icon_u44f0b/4486a7af86e50ae96f5ee3b1b001f3a3.png",
        "rarity": 3,
        "element_type": 0,
        "profession": 5
      },
      {
        "id": 13128,
        "name": "Ghế Lái Rền Vang",
        "icon": "https://act-webstatic.hoyoverse.com/darkmatter/nap/prod_gf_cn/item_icon_u44f0b/db75b9aa2eb3905cb747466cb5d96f27.png",
        "rarity": 3,
        "element_type": 0,
        "profession": 3
      },
      {
        "id": 13135,
        "name": "Dao Rọc Giấy",
        "icon": "https://act-webstatic.hoyoverse.com/darkmatter/nap/prod_gf_cn/item_icon_u44f0b/6fccbd9e42c320d3532d57137fc2eafc.png",
        "rarity": 3,
        "element_type": 0,
        "profession": 2
      },
      {
        "id": 14001,
        "name": "Con Quay Cannon",
        "icon": "https://act-webstatic.hoyoverse.com/darkmatter/nap/prod_gf_cn/item_icon_u44f0b/590a8862bdba369b68518b30c34f6b78.png",
        "rarity": 3,
        "element_type": 0,
        "profession": 1
      },
      {
        "id": 14002,
        "name": "Bóng Bay Tự Do",
        "icon": "https://act-webstatic.hoyoverse.com/darkmatter/nap/prod_gf_cn/item_icon_u44f0b/8bf6059dc316b7ed77c2c775b6967749.png",
        "rarity": 3,
        "element_type": 0,
        "profession": 4
      },
      {
        "id": 14003,
        "name": "Khẩu Súng Ổ Xoay",
        "icon": "https://act-webstatic.hoyoverse.com/darkmatter/nap/prod_gf_cn/item_icon_u44f0b/11f7e8c444365fd5c9872283fcc4cf7d.png",
        "rarity": 3,
        "element_type": 0,
        "profession": 2
      },
      {
        "id": 14102,
        "name": "Đệm Thịt Thép",
        "icon": "https://act-webstatic.hoyoverse.com/darkmatter/nap/prod_gf_cn/item_icon_u44f0b/f6924967b9a1181077dadea32ad73112.png",
        "rarity": 4,
        "element_type": 0,
        "profession": 1
      },
      {
        "id": 14104,
        "name": "Đá Lưu Huỳnh",
        "icon": "https://act-webstatic.hoyoverse.com/darkmatter/nap/prod_gf_cn/item_icon_u44f0b/cc9345868411232f61a82a35d713339b.png",
        "rarity": 4,
        "element_type": 0,
        "profession": 1
      },
      {
        "id": 14107,
        "name": "Nanh Nhọn Tập Kích",
        "icon": "https://act-webstatic.hoyoverse.com/darkmatter/nap/prod_gf_cn/item_icon_u44f0b/bca5377ddf8e73bc44f522a1c400fecf.png",
        "rarity": 4,
        "element_type": 0,
        "profession": 5
      },
      {
        "id": 14109,
        "name": "Sảnh Đường Tuyết Rơi",
        "icon": "https://act-webstatic.hoyoverse.com/darkmatter/nap/prod_gf_cn/item_icon_u44f0b/096dfbc4b565cc6be34cd005f5cb41be.png",
        "rarity": 4,
        "element_type": 0,
        "profession": 3
      },
      {
        "id": 14110,
        "name": "Bánh Răng Thiêu Đốt",
        "icon": "https://act-webstatic.hoyoverse.com/darkmatter/nap/prod_gf_cn/item_icon_u44f0b/852da41cef02d5a180d6f17071778736.png",
        "rarity": 4,
        "element_type": 0,
        "profession": 2
      },
      {
        "id": 14114,
        "name": "Người Trói Buộc",
        "icon": "https://act-webstatic.hoyoverse.com/darkmatter/nap/prod_gf_cn/item_icon_u44f0b/892bbb1c6a1802317bc85cfcc643aef9.png",
        "rarity": 4,
        "element_type": 0,
        "profession": 2
      },
      {
        "id": 14116,
        "name": "Vòng Nguyệt Quế Rực Rỡ",
        "icon": "https://act-webstatic.hoyoverse.com/darkmatter/nap/prod_gf_cn/item_icon_u44f0b/1be28e617f1604b9cd677182c547e3ae.png",
        "rarity": 4,
        "element_type": 0,
        "profession": 2
      },
      {
        "id": 14117,
        "name": "Bình Lắc Lửa Thiêu",
        "icon": "https://act-webstatic.hoyoverse.com/darkmatter/nap/prod_gf_cn/item_icon_u44f0b/ca63b40d32a2372872692660fa55de6e.png",
        "rarity": 4,
        "element_type": 0,
        "profession": 3
      },
      {
        "id": 14118,
        "name": "Trình Biên Dịch Tích Hợp",
        "icon": "https://act-webstatic.hoyoverse.com/darkmatter/nap/prod_gf_cn/item_icon_u44f0b/772565e2019ed920ecd2c15a28380b71.png",
        "rarity": 4,
        "element_type": 0,
        "profession": 3
      },
      {
        "id": 14119,
        "name": "Vị Khách Biển Sâu",
        "icon": "https://act-webstatic.hoyoverse.com/darkmatter/nap/prod_gf_cn/item_icon_u44f0b/6c98f820ae03a26d301955fdee9fdbac.png",
        "rarity": 4,
        "element_type": 0,
        "profession": 1
      },
      {
        "id": 14120,
        "name": "Hộp Thuốc Tàn Tâm",
        "icon": "https://act-webstatic.hoyoverse.com/darkmatter/nap/prod_gf_cn/item_icon_u44f0b/36e68cc751bced838e0e7002a9718c4f.png",
        "rarity": 4,
        "element_type": 0,
        "profession": 1
      },
      {
        "id": 14121,
        "name": "Chiếc Nôi Nức Nở",
        "icon": "https://act-webstatic.hoyoverse.com/darkmatter/nap/prod_gf_cn/item_icon_u44f0b/a5cc50f4ce67ff62ac69da1b8c206d4b.png",
        "rarity": 4,
        "element_type": 0,
        "profession": 4
      },
      {
        "id": 14122,
        "name": "Hiền Giả Thời Gian",
        "icon": "https://act-webstatic.hoyoverse.com/darkmatter/nap/prod_gf_cn/item_icon_u44f0b/52234534c59c5a71468566f2760a9674.png",
        "rarity": 4,
        "element_type": 0,
        "profession": 3
      },
      {
        "id": 14124,
        "name": "Chống Bạo Động VI",
        "icon": "https://act-webstatic.hoyoverse.com/darkmatter/nap/prod_gf_cn/item_icon_u44f0b/63c8b2dbb5fd12eff8371262f256d034.png",
        "rarity": 4,
        "element_type": 0,
        "profession": 1
      },
      {
        "id": 14125,
        "name": "Ngọc Hồ Thanh Băng",
        "icon": "https://act-webstatic.hoyoverse.com/darkmatter/nap/prod_gf_cn/item_icon_u44f0b/7898133ae44593b07a10848d50141b45.png",
        "rarity": 4,
        "element_type": 0,
        "profession": 2
      },
      {
        "id": 14126,
        "name": "Gọng Kìm Sắc Bén",
        "icon": "https://act-webstatic.hoyoverse.com/darkmatter/nap/prod_gf_cn/item_icon_u44f0b/f99fde35e5d77b2f8e7ad2c21dd2a96c.png",
        "rarity": 4,
        "element_type": 0,
        "profession": 3
      },
      {
        "id": 14131,
        "name": "Hộp Trang Điểm Sành Điệu",
        "icon": "https://act-webstatic.hoyoverse.com/darkmatter/nap/prod_gf_cn/item_icon_u44f0b/14fbaf6aa8dcfc1fea769e297e0777cd.png",
        "rarity": 4,
        "element_type": 0,
        "profession": 4
      },
      {
        "id": 14132,
        "name": "Tiếng Lòng Trong Đêm",
        "icon": "https://act-webstatic.hoyoverse.com/darkmatter/nap/prod_gf_cn/item_icon_u44f0b/ef18c59ec9428d08f4ffbf3f2d9f029c.png",
        "rarity": 4,
        "element_type": 0,
        "profession": 1
      },
      {
        "id": 14136,
        "name": "Ánh Mắt Tìm Hồn",
        "icon": "https://act-webstatic.hoyoverse.com/darkmatter/nap/prod_gf_cn/item_icon_u44f0b/c375fc70d11ab4cc0d7a03ffdbe6bb19.png",
        "rarity": 4,
        "element_type": 0,
        "profession": 2
      },
      {
        "id": 14138,
        "name": "Hy Sinh Thuần Khiết",
        "icon": "https://act-webstatic.hoyoverse.com/darkmatter/nap/prod_gf_cn/item_icon_u44f0b/c019a4257f2b9733dd62f31b23d4bf16.png",
        "rarity": 4,
        "element_type": 0,
        "profession": 1
      },
      {
        "id": 53001,
        "name": "Boo Cánh Cụt",
        "icon": "https://act-webstatic.hoyoverse.com/darkmatter/nap/prod_gf_cn/item_icon_u44f0b/1dfd2f10e3a349fb5cd12436c08e2ca9.png",
        "rarity": 3,
        "element_type": 0,
        "profession": 0
      },
      {
        "id": 53002,
        "name": "Boo Chiêu Tài",
        "icon": "https://act-webstatic.hoyoverse.com/darkmatter/nap/prod_gf_cn/item_icon_u44f0b/2d395da3ac6ddaf46aec27d6fcb36613.png",
        "rarity": 3,
        "element_type": 0,
        "profession": 0
      },
      {
        "id": 53003,
        "name": "Boo Tầm Bảo",
        "icon": "https://act-webstatic.hoyoverse.com/darkmatter/nap/prod_gf_cn/item_icon_u44f0b/584ff8778e135b6f01a21fda2438fea8.png",
        "rarity": 3,
        "element_type": 0,
        "profession": 0
      },
      {
        "id": 53004,
        "name": "Boo Sumo",
        "icon": "https://act-webstatic.hoyoverse.com/darkmatter/nap/prod_gf_cn/item_icon_u44f0b/1937513538edcc08d19497eede1ff12a.png",
        "rarity": 3,
        "element_type": 0,
        "profession": 0
      },
      {
        "id": 53005,
        "name": "Boo Vỏ Giấy",
        "icon": "https://act-webstatic.hoyoverse.com/darkmatter/nap/prod_gf_cn/item_icon_u44f0b/b3615286a99d409b2e26783af8f0a533.png",
        "rarity": 3,
        "element_type": 0,
        "profession": 0
      },
      {
        "id": 53006,
        "name": "Boo Túi Giấy",
        "icon": "https://act-webstatic.hoyoverse.com/darkmatter/nap/prod_gf_cn/item_icon_u44f0b/81abfa4c530c82d7ff60eabd07cb7528.png",
        "rarity": 3,
        "element_type": 0,
        "profession": 0
      },
      {
        "id": 53007,
        "name": "Boo Khóc Nhè",
        "icon": "https://act-webstatic.hoyoverse.com/darkmatter/nap/prod_gf_cn/item_icon_u44f0b/7e4bf2ede5a63543bcb952424cbc9456.png",
        "rarity": 3,
        "element_type": 0,
        "profession": 0
      },
      {
        "id": 53008,
        "name": "Boo Hạt Bơ",
        "icon": "https://act-webstatic.hoyoverse.com/darkmatter/nap/prod_gf_cn/item_icon_u44f0b/11a1ac15216333373588dbd04832283e.png",
        "rarity": 3,
        "element_type": 0,
        "profession": 0
      },
      {
        "id": 53009,
        "name": "Boo Bia Bắn",
        "icon": "https://act-webstatic.hoyoverse.com/darkmatter/nap/prod_gf_cn/item_icon_u44f0b/55215f11c09438e3ba3a7127fe9ae8ad.png",
        "rarity": 3,
        "element_type": 0,
        "profession": 0
      },
      {
        "id": 53010,
        "name": "Boo Điện Giật",
        "icon": "https://act-webstatic.hoyoverse.com/darkmatter/nap/prod_gf_cn/item_icon_u44f0b/385a19163fcb2b1fe636526efb0c7eaa.png",
        "rarity": 3,
        "element_type": 0,
        "profession": 0
      },
      {
        "id": 53011,
        "name": "Boo Từ Trường",
        "icon": "https://act-webstatic.hoyoverse.com/darkmatter/nap/prod_gf_cn/item_icon_u44f0b/9f74abd65b8b79d88829735948965179.png",
        "rarity": 3,
        "element_type": 0,
        "profession": 0
      },
      {
        "id": 53012,
        "name": "Boo Khí Nén",
        "icon": "https://act-webstatic.hoyoverse.com/darkmatter/nap/prod_gf_cn/item_icon_u44f0b/9e363518cba8ed0ce2c80c40f671ef99.png",
        "rarity": 3,
        "element_type": 0,
        "profession": 0
      },
      {
        "id": 53013,
        "name": "Boo Bất Lương",
        "icon": "https://act-webstatic.hoyoverse.com/darkmatter/nap/prod_gf_cn/item_icon_u44f0b/7c1668b27c5aebad45ceca152589369f.png",
        "rarity": 3,
        "element_type": 0,
        "profession": 0
      },
      {
        "id": 53015,
        "name": "Boo Đấu Sĩ",
        "icon": "https://act-webstatic.hoyoverse.com/darkmatter/nap/prod_gf_cn/item_icon_u44f0b/ac4ce4b8d5857af1f1b3bb2228b83644.png",
        "rarity": 3,
        "element_type": 0,
        "profession": 0
      },
      {
        "id": 53017,
        "name": "Boo Kỵ Sĩ",
        "icon": "https://act-webstatic.hoyoverse.com/darkmatter/nap/prod_gf_cn/item_icon_u44f0b/9158599929b8f2d70aaa5986603ccf30.png",
        "rarity": 3,
        "element_type": 0,
        "profession": 0
      },
      {
        "id": 54001,
        "name": "Boo Cá Mập",
        "icon": "https://act-webstatic.hoyoverse.com/darkmatter/nap/prod_gf_cn/item_icon_u44f0b/0ecd617e29f32969a896c97f443edbb8.png",
        "rarity": 4,
        "element_type": 0,
        "profession": 0
      },
      {
        "id": 54002,
        "name": "Safety",
        "icon": "https://act-webstatic.hoyoverse.com/darkmatter/nap/prod_gf_cn/item_icon_u44f0b/c86a45c744195c9b833c2b412444747b.png",
        "rarity": 4,
        "element_type": 0,
        "profession": 0
      },
      {
        "id": 54003,
        "name": "Boo Ác Ma",
        "icon": "https://act-webstatic.hoyoverse.com/darkmatter/nap/prod_gf_cn/item_icon_u44f0b/7094fe66c57b838661276d0fab6442eb.png",
        "rarity": 3,
        "element_type": 0,
        "profession": 0
      },
      {
        "id": 54004,
        "name": "Butler",
        "icon": "https://act-webstatic.hoyoverse.com/darkmatter/nap/prod_gf_cn/item_icon_u44f0b/e2596aad13214ef09908ec5c7b2528e5.png",
        "rarity": 4,
        "element_type": 0,
        "profession": 0
      },
      {
        "id": 54005,
        "name": "Amillion",
        "icon": "https://act-webstatic.hoyoverse.com/darkmatter/nap/prod_gf_cn/item_icon_u44f0b/e3031108ed628d8968684ed3e5ef3566.png",
        "rarity": 4,
        "element_type": 0,
        "profession": 0
      },
      {
        "id": 54006,
        "name": "Boo Tốc Độ",
        "icon": "https://act-webstatic.hoyoverse.com/darkmatter/nap/prod_gf_cn/item_icon_u44f0b/ba2b6751557e05de40ad2e8e349da039.png",
        "rarity": 4,
        "element_type": 0,
        "profession": 0
      },
      {
        "id": 54008,
        "name": "Boo Trình Cắm",
        "icon": "https://act-webstatic.hoyoverse.com/darkmatter/nap/prod_gf_cn/item_icon_u44f0b/417484bff2f96b97ffae8d261fe97244.png",
        "rarity": 4,
        "element_type": 0,
        "profession": 0
      },
      {
        "id": 54009,
        "name": "Boo Cộng Hưởng",
        "icon": "https://act-webstatic.hoyoverse.com/darkmatter/nap/prod_gf_cn/item_icon_u44f0b/31c1dc4f1a04553a174d3bc989f082fd.png",
        "rarity": 4,
        "element_type": 0,
        "profession": 0
      },
      {
        "id": 54011,
        "name": "Red Moccus",
        "icon": "https://act-webstatic.hoyoverse.com/darkmatter/nap/prod_gf_cn/item_icon_u44f0b/3a87b70793e442fcda24422a7335fe28.png",
        "rarity": 4,
        "element_type": 0,
        "profession": 0
      },
      {
        "id": 54012,
        "name": "Tuần Vệ Cui",
        "icon": "https://act-webstatic.hoyoverse.com/darkmatter/nap/prod_gf_cn/item_icon_u44f0b/262935c9933dffc633111a0b95ebaafd.png",
        "rarity": 4,
        "element_type": 0,
        "profession": 0
      },
      {
        "id": 54013,
        "name": "Boo Pằng Pằng",
        "icon": "https://act-webstatic.hoyoverse.com/darkmatter/nap/prod_gf_cn/item_icon_u44f0b/92a1d10df43bb613a6e68b85f621397d.png",
        "rarity": 4,
        "element_type": 0,
        "profession": 0
      },
      {
        "id": 54014,
        "name": "Đặc Vụ Gulliver",
        "icon": "https://act-webstatic.hoyoverse.com/darkmatter/nap/prod_gf_cn/item_icon_u44f0b/bd77b8727fe5d740ecdac607b7e9d460.png",
        "rarity": 4,
        "element_type": 0,
        "profession": 0
      },
      {
        "id": 54015,
        "name": "Snap",
        "icon": "https://act-webstatic.hoyoverse.com/darkmatter/nap/prod_gf_cn/item_icon_u44f0b/b95efc17c40f64abc4d5694ef16651a3.png",
        "rarity": 4,
        "element_type": 0,
        "profession": 0
      }
    ]
  }
}